mycli/__init__.py
mycli/echo.py
mycli/version.py
mycli/osc/__init__.py
mycli/osc/plugin.py
python_cliclient-1.0.0.dist-info/DESCRIPTION.rst
python_cliclient-1.0.0.dist-info/METADATA
python_cliclient-1.0.0.dist-info/RECORD
python_cliclient-1.0.0.dist-info/WHEEL
python_cliclient-1.0.0.dist-info/entry_points.txt
python_cliclient-1.0.0.dist-info/metadata.json
python_cliclient-1.0.0.dist-info/pbr.json
python_cliclient-1.0.0.dist-info/top_level.txt
