Metadata-Version: 2.0
Name: python-cliclient
Version: 1.0.0
Summary: python-cliclient
Home-page: UNKNOWN
Author: Lingxian Kong
Author-email: anlin.kong@gmail.com
License: Apache License, Version 2.0
Platform: UNKNOWN
Classifier: Development Status :: 4 - Beta
Classifier: Environment :: Console
Classifier: Environment :: OpenStack
Classifier: Intended Audience :: Developers
Classifier: Intended Audience :: Information Technology
Classifier: Intended Audience :: System Administrators
Classifier: License :: OSI Approved :: Apache Software License
Classifier: Operating System :: POSIX :: Linux
Classifier: Programming Language :: Python
Classifier: Programming Language :: Python :: 2
Classifier: Programming Language :: Python :: 2.7
Classifier: Programming Language :: Python :: 3
Classifier: Programming Language :: Python :: 3.5
Requires-Dist: pbr (!=2.1.0,>=2.0.0)
Requires-Dist: python-openstackclient (>=3.12.0)
